spm_runtime/__init__.py
spm_runtime/__main__.py
spm_runtime/_endpoint.py
spm_runtime/_standalone.py
spm_runtime/_version.py
spm_runtime/_spm/__init__.py
spm_runtime/_spm/_spm.ctf
spm_runtime_r2021b-25.1.2.post2.dist-info/licenses/LICENSE
spm_runtime_r2021b-25.1.2.post2.dist-info/METADATA
spm_runtime_r2021b-25.1.2.post2.dist-info/WHEEL
spm_runtime_r2021b-25.1.2.post2.dist-info/entry_points.txt
spm_runtime_r2021b-25.1.2.post2.dist-info/top_level.txt
spm_runtime_r2021b-25.1.2.post2.dist-info/RECORD
